db_classes/DbClass.py
db_classes/DbClassLiteral.py
db_classes/__init__.py
db_classes/JsonEncoder/Decoder.py
db_classes/JsonEncoder/DefaultJsonEncoder.py
db_classes/JsonEncoder/Encoder.py
db_classes/JsonEncoder/JsonOperator.py
db_classes/JsonEncoder/__init__.py
db_classes/JsonEncoder/Decoders/DatetimeDecoder.py
db_classes/JsonEncoder/Decoders/DecimalDecoder.py
db_classes/JsonEncoder/Decoders/__init__.py
db_classes/JsonEncoder/Encoders/DataclassEncoder.py
db_classes/JsonEncoder/Encoders/DatetimeEncoder.py
db_classes/JsonEncoder/Encoders/DecimalEncoder.py
db_classes/JsonEncoder/Encoders/__init__.py
db_classes-0.0.4.dist-info/LICENSE
db_classes-0.0.4.dist-info/METADATA
db_classes-0.0.4.dist-info/WHEEL
db_classes-0.0.4.dist-info/top_level.txt
db_classes-0.0.4.dist-info/RECORD
