Metadata-Version: 2.1
Name: db-classes
Version: 0.0.4
Summary: Highly serializable implementation of dataclass ment to work with databases
Home-page: https://github.com/Tesla2000/db_class
Author: Tesla2000
Author-email: fratajczak124@gmail.com
Project-URL: Homepage, https://github.com/Tesla2000/db_class
Classifier: Programming Language :: Python :: 3
Classifier: License :: OSI Approved :: MIT License
Classifier: Operating System :: OS Independent
Requires-Python: >=3.11
License-File: LICENSE
Requires-Dist: dacite >=1.8.1
